pyosv/__init__.py
pyosv/ai/__init__.py
pyosv/ai/clustering.py
pyosv/ai/data_reduction.py
pyosv/freq/__init__.py
pyosv/freq/fft.py
pyosv/freq/filters.py
pyosv/io/__init__.py
pyosv/io/batch_reader.py
pyosv/io/reader.py
pyosv/io/writer.py
pyosv/plot/__init__.py
pyosv/plot/cube.py
pyosv/plot/geo.py
pyosv/plot/plot.py
pyosv/post/__init__.py
pyosv/post/composite.py
pyosv/post/normalized_difference.py
pyosv/post/patch_extractor.py
pyosv/pre/__init__.py
pyosv/pre/hist_normalizer.py
pyosv/pre/normalizer.py
pyosv/pre/normalizer_bands.py
pyosv/utils/__init__.py
pyosv/utils/mapper.py
pyosv/utils/paths.py
pyosv/utils/printer.py
tests/__init__.py
pyosv-0.0.37.dist-info/LICENSE
pyosv-0.0.37.dist-info/METADATA
pyosv-0.0.37.dist-info/WHEEL
pyosv-0.0.37.dist-info/top_level.txt
pyosv-0.0.37.dist-info/RECORD
