Metadata-Version: 2.2
Name: pyosv
Version: 0.0.37
Summary: Python Open Satellite Vision
Home-page: https://github.com/alessandrosebastianelli/opensv.git
Author: Alessandro Sebastianelli
Author-email: Alessandro Sebastianelli <alessandro.sebastianelli1995@gmail.com>
License: Copyright (c) 2023-2023 Alessandro Sebastianelli
Project-URL: Homepage, https://github.com/alessandrosebastianelli/opensv
Project-URL: Bug Tracker, https://github.com/alessandrosebastianelli/opensv/issues
Classifier: Programming Language :: Python :: 3
Classifier: License :: OSI Approved :: MIT License
Classifier: Operating System :: OS Independent
Requires-Python: >=3.7
License-File: LICENSE
Requires-Dist: numpy
Requires-Dist: rasterio
Requires-Dist: scikit-learn
Requires-Dist: tqdm
Requires-Dist: matplotlib
Requires-Dist: scipy
Requires-Dist: cartopy
Requires-Dist: pyproj
Requires-Dist: pyqt5
Requires-Dist: netCDF4
Requires-Dist: pillow
Dynamic: author
Dynamic: home-page
